rix_template/__init__.py
rix_template/run.py
rix_template/providers/__init__.py
rix_template/providers/shared_state.py
rix_template/providers/version.py
rix_template-0.0.6.dist-info/LICENSE
rix_template-0.0.6.dist-info/LICENSE.md
rix_template-0.0.6.dist-info/METADATA
rix_template-0.0.6.dist-info/WHEEL
rix_template-0.0.6.dist-info/entry_points.txt
rix_template-0.0.6.dist-info/top_level.txt
rix_template-0.0.6.dist-info/RECORD
