Metadata-Version: 2.1
Name: rix-template
Version: 0.0.6
Summary: Full template for python web projects with Docker, GitHub Actions, PyPI, and more.
Home-page: https://github.com/rix1337/Python-Template
Author: rix1337
Author-email: 
License: UNKNOWN
Platform: UNKNOWN
Classifier: Programming Language :: Python :: 3
Classifier: License :: OSI Approved :: MIT License
Classifier: Operating System :: OS Independent
License-File: LICENSE
License-File: LICENSE.md
Requires-Dist: bottle (==0.12.25)
